historian/sqlite/__init__.py
historian/sqlite/sqlitefuncts.py
volttron_sqlite_historian-2.0.0rc1.dist-info/LICENSE
volttron_sqlite_historian-2.0.0rc1.dist-info/METADATA
volttron_sqlite_historian-2.0.0rc1.dist-info/WHEEL
volttron_sqlite_historian-2.0.0rc1.dist-info/entry_points.txt
volttron_sqlite_historian-2.0.0rc1.dist-info/RECORD
