Metadata-Version: 2.3
Name: volttron-sqlite-historian
Version: 2.0.0rc1
Summary: VOLTTRON historian that store data in sqlite3 database
License: Apache-2.0
Author: VOLTTRON Team
Author-email: volttron@pnnl.gov
Requires-Python: >=3.10,<4.0
Classifier: License :: OSI Approved :: Apache Software License
Classifier: Programming Language :: Python :: 3
Classifier: Programming Language :: Python :: 3.10
Classifier: Programming Language :: Python :: 3.11
Classifier: Programming Language :: Python :: 3.12
Classifier: Programming Language :: Python :: 3.13
Requires-Dist: volttron-lib-sql-historian (>=2.0.0rc1)
Project-URL: Homepage, https://github.com/VOLTTRON/volttron-sqlite-historian
Project-URL: Repository, https://github.com/VOLTTRON/volttron-sqlite-historian
